pymsteams/__init__.py
pymsteams_bin-0.2.2.dist-info/LICENSE
pymsteams_bin-0.2.2.dist-info/METADATA
pymsteams_bin-0.2.2.dist-info/WHEEL
pymsteams_bin-0.2.2.dist-info/top_level.txt
pymsteams_bin-0.2.2.dist-info/RECORD
