Metadata-Version: 2.1
Name: pymsteams-bin
Version: 0.2.2
Summary: Format messages and post to Microsoft Teams.
Home-page: https://github.com/rveachkc/pymsteams
Author: Ryan Veach
Author-email: rveach@gmail.com
License: Apache
Keywords: Microsoft,Teams
Classifier: Development Status :: 5 - Production/Stable
Classifier: Intended Audience :: Developers
Classifier: Intended Audience :: Information Technology
Classifier: Intended Audience :: System Administrators
Classifier: License :: OSI Approved :: Apache Software License
Classifier: Operating System :: OS Independent
Classifier: Topic :: Software Development :: Libraries :: Python Modules
Classifier: Topic :: Internet
Classifier: Programming Language :: Python :: 3
Classifier: Topic :: Office/Business
Classifier: Topic :: Office/Business :: Groupware
Requires-Python: >=3.6
License-File: LICENSE
Requires-Dist: requests >=2.20.0
Provides-Extra: async
Requires-Dist: httpx >=0.18.2 ; extra == 'async'
